[
  {
    "id": "dw-1014",
    "alert_id": "DW-1014",
    "alert_name": "Airflow Scheduler Down",
    "alert_type": "scheduler",
    "title": "Airflow Scheduler Down",
    "service": "airflow",
    "severity": "CRITICAL",
    "recommended_action": "Investigate issue",
    "description": "Service: airflow",
    "source": "rag-incident"
  },
  {
    "id": "dw-1017",
    "alert_id": "DW-1017",
    "alert_name": "Business SLA Missed",
    "alert_type": "sla_breach",
    "title": "Business SLA Missed",
    "service": "daily-sales-report",
    "severity": "CRITICAL",
    "recommended_action": "Investigate issue",
    "description": "Service: daily-sales-report",
    "source": "rag-incident"
  },
  {
    "id": "dw-1020",
    "alert_id": "DW-1020",
    "alert_name": "Dashboard Refresh Failure",
    "alert_type": "reporting",
    "title": "Dashboard Refresh Failure",
    "service": "powerbi-reporting",
    "severity": "HIGH",
    "recommended_action": "Investigate issue",
    "description": "Service: powerbi-reporting",
    "source": "rag-incident"
  },
  {
    "id": "dw-1002",
    "alert_id": "DW-1002",
    "alert_name": "Data Load Delay",
    "alert_type": "sla_breach",
    "title": "Data Load Delay",
    "service": "data-ingestion",
    "severity": "HIGH",
    "recommended_action": "Investigate issue",
    "description": "Service: data-ingestion",
    "source": "rag-incident"
  },
  {
    "id": "dw-1018",
    "alert_id": "DW-1018",
    "alert_name": "Data Pipeline Backlog Growing",
    "alert_type": "backlog",
    "title": "Data Pipeline Backlog Growing",
    "service": "data-pipeline",
    "severity": "HIGH",
    "recommended_action": "Investigate issue",
    "description": "Service: data-pipeline",
    "source": "rag-incident"
  },
  {
    "id": "dw-1005",
    "alert_id": "DW-1005",
    "alert_name": "Data Quality Check Failed",
    "alert_type": "data_quality",
    "title": "Data Quality Check Failed",
    "service": "dq-framework",
    "severity": "CRITICAL",
    "recommended_action": "Investigate issue",
    "description": "Service: dq-framework",
    "source": "rag-incident"
  },
  {
    "id": "dw-1012",
    "alert_id": "DW-1012",
    "alert_name": "Dimension Load Failure",
    "alert_type": "etl_failure",
    "title": "Dimension Load Failure",
    "service": "customer-dimension",
    "severity": "HIGH",
    "recommended_action": "Investigate issue",
    "description": "Service: customer-dimension",
    "source": "rag-incident"
  },
  {
    "id": "dw-1001",
    "alert_id": "DW-1001",
    "alert_name": "ETL Job Failure",
    "alert_type": "etl_failure",
    "title": "ETL Job Failure",
    "service": "airflow",
    "severity": "CRITICAL",
    "recommended_action": "Investigate issue",
    "description": "Service: airflow",
    "source": "rag-incident"
  },
  {
    "id": "dw-1013",
    "alert_id": "DW-1013",
    "alert_name": "Fact Table Record Count Mismatch",
    "alert_type": "reconciliation",
    "title": "Fact Table Record Count Mismatch",
    "service": "sales-fact",
    "severity": "CRITICAL",
    "recommended_action": "Investigate issue",
    "description": "Service: sales-fact",
    "source": "rag-incident"
  },
  {
    "id": "dw-1016",
    "alert_id": "DW-1016",
    "alert_name": "Failed CDC Processing",
    "alert_type": "change_data_capture",
    "title": "Failed CDC Processing",
    "service": "cdc-pipeline",
    "severity": "CRITICAL",
    "recommended_action": "Investigate issue",
    "description": "Service: cdc-pipeline",
    "source": "rag-incident"
  },
  {
    "id": "inc-9102-mysql-unavailable",
    "alert_id": "INC-9102-MYSQL-UNAVAILABLE",
    "alert_name": "inc 9102 mysql unavailable",
    "title": "inc 9102 mysql unavailable",
    "service": "unknown",
    "severity": "HIGH",
    "recommended_action": "Investigate issue",
    "description": "The MySQL monitor raises `MySQLUnavailable` alerts when it cannot authenticate or connect to the configured MySQL endpoint.",
    "source": "rag-incident"
  },
  {
    "id": "inc-8842-payment-latency-after-deployment-2-5",
    "alert_id": "INC-8842-PAYMENT-LATENCY-AFTER-DEPLOYMENT-2-5",
    "alert_name": "INC-8842 payment latency after Deployment 2.5",
    "title": "INC-8842 payment latency after Deployment 2.5",
    "service": "payments",
    "severity": "HIGH",
    "recommended_action": "Investigate issue",
    "description": "Deployment 2.5 increased checkout p95 latency for payments. Rollback restored",
    "deployment": "Deployment 2.5",
    "source": "rag-incident"
  },
  {
    "id": "inc-9011-orders-database-replica-lag",
    "alert_id": "INC-9011-ORDERS-DATABASE-REPLICA-LAG",
    "alert_name": "INC-9011 orders database replica lag",
    "title": "INC-9011 orders database replica lag",
    "service": "orders-db",
    "severity": "HIGH",
    "recommended_action": "Investigate issue",
    "description": "Orders read replicas lagged behind the primary after a write-heavy campaign.",
    "source": "rag-incident"
  },
  {
    "id": "dw-1004",
    "alert_id": "DW-1004",
    "alert_name": "Kafka Consumer Lag High",
    "alert_type": "streaming",
    "title": "Kafka Consumer Lag High",
    "service": "kafka-ingestion",
    "severity": "HIGH",
    "recommended_action": "Investigate issue",
    "description": "Service: kafka-ingestion",
    "source": "rag-incident"
  },
  {
    "id": "dw-1011",
    "alert_id": "DW-1011",
    "alert_name": "Late Arriving Data",
    "alert_type": "data_latency",
    "title": "Late Arriving Data",
    "service": "transaction-feed",
    "severity": "HIGH",
    "recommended_action": "Investigate issue",
    "description": "Service: transaction-feed",
    "source": "rag-incident"
  },
  {
    "id": "dw-1006",
    "alert_id": "DW-1006",
    "alert_name": "Missing Daily Partition",
    "alert_type": "partition_missing",
    "title": "Missing Daily Partition",
    "service": "sales-fact-table",
    "severity": "HIGH",
    "recommended_action": "Investigate issue",
    "description": "Service: sales-fact-table",
    "source": "rag-incident"
  },
  {
    "id": "dw-1008",
    "alert_id": "DW-1008",
    "alert_name": "Query Performance Degradation",
    "alert_type": "performance",
    "title": "Query Performance Degradation",
    "service": "data-warehouse",
    "severity": "HIGH",
    "recommended_action": "Investigate issue",
    "description": "Service: data-warehouse",
    "source": "rag-incident"
  },
  {
    "id": "rag-doc",
    "alert_id": "RAG-DOC",
    "alert_name": "RAG_doc",
    "title": "RAG_doc",
    "service": "unknown",
    "severity": "HIGH",
    "recommended_action": "Investigate issue",
    "description": "PK\u0003\u0004\u0014\u0000\u0006\u0000\b\u0000\u0000\u0000!\u0000\u00df\u00a4\u00d2lZ\u0001\u0000\u0000 \u0005\u0000\u0000\u0013\u0000\b\u0002[Content_Types].xml \u00a2\u0004\u0002(\u00a0\u0000\u0002\u0000\u0000\u0000\u0000\u0000\u0000\u0000\u0000\u0000\u0000\u0000\u0000\u0000\u0000\u0000\u0000\u0000\u0000\u0000\u0000\u0000\u0000\u0000\u0000\u0000\u0000\u0000\u0000\u0000\u0000\u0000\u0000\u0000\u0000\u0000\u0000\u0000\u0000\u0000\u0000\u0000\u0000\u0000\u0000\u0000\u0000\u0000\u0000\u0000\u0000\u0000\u0000\u0000\u0000\u0000\u0000\u0000\u0000\u0000\u0000\u0000\u0000\u0000\u0000\u0000\u0000\u0000\u0000\u0000\u0000\u0000\u0000\u0000\u0000\u0000\u0000\u0000\u0000\u0000\u0000\u0000\u0000\u0000\u0000\u0000\u0000\u0000\u0000\u0000\u0000\u0000\u0000\u0000\u0000\u0000\u0000\u0000\u0000\u0000\u0000\u0000\u0000\u0000\u0000\u0000\u0000\u0000\u0000\u0000\u0000\u0000\u0000\u0000\u0000\u0000\u0000\u0000\u0000\u0000\u0000\u0000\u0000\u0000\u0000\u0000\u0000\u0000\u0000\u0000\u0000\u0000\u0000\u0000\u0000\u0000\u0000\u0000\u0000\u0000\u0000\u0000\u0000\u0000\u0000\u0000\u0000\u0000\u0000\u0000\u0000\u0000\u0000\u0000\u0000\u0000\u0000\u0000\u0000\u0000\u0000\u0000\u0000\u0000",
    "source": "rag-incident"
  },
  {
    "id": "dw-1009",
    "alert_id": "DW-1009",
    "alert_name": "Replication Lag Exceeded Threshold",
    "alert_type": "replication",
    "title": "Replication Lag Exceeded Threshold",
    "service": "replication-service",
    "severity": "HIGH",
    "recommended_action": "Investigate issue",
    "description": "Service: replication-service",
    "source": "rag-incident"
  },
  {
    "id": "dw-1010",
    "alert_id": "DW-1010",
    "alert_name": "Schema Drift Detected",
    "alert_type": "schema_change",
    "title": "Schema Drift Detected",
    "service": "customer-ingestion",
    "severity": "CRITICAL",
    "recommended_action": "Investigate issue",
    "description": "Service: customer-ingestion",
    "source": "rag-incident"
  },
  {
    "id": "dw-1003",
    "alert_id": "DW-1003",
    "alert_name": "Source System Unavailable",
    "alert_type": "source_connectivity",
    "title": "Source System Unavailable",
    "service": "oracle-source",
    "severity": "CRITICAL",
    "recommended_action": "Investigate issue",
    "description": "Service: oracle-source",
    "source": "rag-incident"
  },
  {
    "id": "dw-1015",
    "alert_id": "DW-1015",
    "alert_name": "Spark Executor Memory Exhausted",
    "alert_type": "resource_utilization",
    "title": "Spark Executor Memory Exhausted",
    "service": "spark-cluster",
    "severity": "HIGH",
    "recommended_action": "Investigate issue",
    "description": "Service: spark-cluster",
    "source": "rag-incident"
  },
  {
    "id": "dw-1019",
    "alert_id": "DW-1019",
    "alert_name": "Unauthorized Data Access Attempt",
    "alert_type": "security",
    "title": "Unauthorized Data Access Attempt",
    "service": "data-warehouse",
    "severity": "CRITICAL",
    "recommended_action": "Investigate issue",
    "description": "Service: data-warehouse",
    "source": "rag-incident"
  },
  {
    "id": "dw-1007",
    "alert_id": "DW-1007",
    "alert_name": "Warehouse Storage Usage High",
    "alert_type": "capacity",
    "title": "Warehouse Storage Usage High",
    "service": "snowflake",
    "severity": "HIGH",
    "recommended_action": "Investigate issue",
    "description": "Service: snowflake",
    "source": "rag-incident"
  }
]